flask_uuid.py
setup.py
Flask_UUID.egg-info/PKG-INFO
Flask_UUID.egg-info/SOURCES.txt
Flask_UUID.egg-info/dependency_links.txt
Flask_UUID.egg-info/top_level.txt