Metadata-Version: 1.0
Name: Flask-UUID
Version: 0.1
Summary: UUID url converter for Flask routes
Home-page: https://github.com/wbolster/flask-uuid
Author: Wouter Bolsterlee
Author-email: uws@xs4all.nl
License: BSD
Platform: UNKNOWN
